ketrics_dev_tools/KetricsDevTools.py
ketrics_dev_tools/__init__.py
ketrics_dev_tools/command_line.py
ketrics_dev_tools/version.py
ketrics_dev_tools-0.0.2.dist-info/LICENSE
ketrics_dev_tools-0.0.2.dist-info/METADATA
ketrics_dev_tools-0.0.2.dist-info/WHEEL
ketrics_dev_tools-0.0.2.dist-info/entry_points.txt
ketrics_dev_tools-0.0.2.dist-info/top_level.txt
ketrics_dev_tools-0.0.2.dist-info/RECORD
