Metadata-Version: 2.1
Name: ketrics-dev-tools
Version: 0.0.2
Summary: This package is for Ketrics Application Developers
Home-page: https://www.ketrics.com
Author: Cristian Bustamante
Author-email: cristian@ketrics.com
License: UNKNOWN
Project-URL: Documentation, https://github.com/ketrics/ketrics-dev-tools
Project-URL: Source Code, https://github.com/ketrics/ketrics-dev-tools
Keywords: ketrics
Platform: UNKNOWN
Classifier: Programming Language :: Python :: 3
Classifier: License :: OSI Approved :: MIT License
Classifier: Operating System :: OS Independent
Requires-Dist: python-dotenv (>=0.10.3)
Requires-Dist: requests (>=2.22.0)
